MANIFEST.in
README.rst
setup.py
aliyun_python_sdk_afs.egg-info/PKG-INFO
aliyun_python_sdk_afs.egg-info/SOURCES.txt
aliyun_python_sdk_afs.egg-info/dependency_links.txt
aliyun_python_sdk_afs.egg-info/requires.txt
aliyun_python_sdk_afs.egg-info/top_level.txt
aliyunsdkafs/__init__.py
aliyunsdkafs/request/__init__.py
aliyunsdkafs/request/v20180112/AnalyzeNvcRequest.py
aliyunsdkafs/request/v20180112/AuthenticateSigRequest.py
aliyunsdkafs/request/v20180112/ConfigurationStyleRequest.py
aliyunsdkafs/request/v20180112/CreateConfigurationRequest.py
aliyunsdkafs/request/v20180112/DescribeCaptchaDayRequest.py
aliyunsdkafs/request/v20180112/DescribeCaptchaIpCityRequest.py
aliyunsdkafs/request/v20180112/DescribeCaptchaMinRequest.py
aliyunsdkafs/request/v20180112/DescribeCaptchaOrderRequest.py
aliyunsdkafs/request/v20180112/DescribeCaptchaRiskRequest.py
aliyunsdkafs/request/v20180112/DescribeConfigNameRequest.py
aliyunsdkafs/request/v20180112/DescribeEarlyWarningRequest.py
aliyunsdkafs/request/v20180112/DescribeOrderInfoRequest.py
aliyunsdkafs/request/v20180112/DescribePersonMachineListRequest.py
aliyunsdkafs/request/v20180112/SetEarlyWarningRequest.py
aliyunsdkafs/request/v20180112/UpdateConfigNameRequest.py
aliyunsdkafs/request/v20180112/__init__.py